ucloud/__init__.py
ucloud/client.py
ucloud/version.py
ucloud/core/__init__.py
ucloud/core/auth/__init__.py
ucloud/core/auth/_cfg.py
ucloud/core/client/__init__.py
ucloud/core/client/_cfg.py
ucloud/core/client/_client.py
ucloud/core/exc/__init__.py
ucloud/core/exc/_exc.py
ucloud/core/transport/__init__.py
ucloud/core/transport/_requests.py
ucloud/core/transport/http.py
ucloud/core/transport/utils.py
ucloud/core/typesystem/__init__.py
ucloud/core/typesystem/abstract.py
ucloud/core/typesystem/encoder.py
ucloud/core/typesystem/fields.py
ucloud/core/typesystem/schema.py
ucloud/core/utils/__init__.py
ucloud/core/utils/compat.py
ucloud/core/utils/deco.py
ucloud/core/utils/log.py
ucloud/core/utils/middleware.py
ucloud/helpers/__init__.py
ucloud/helpers/utils.py
ucloud/helpers/wait.py
ucloud/services/__init__.py
ucloud/services/cube/__init__.py
ucloud/services/cube/client.py
ucloud/services/cube/schemas/__init__.py
ucloud/services/cube/schemas/apis.py
ucloud/services/cube/schemas/models.py
ucloud/services/iam/__init__.py
ucloud/services/iam/client.py
ucloud/services/iam/schemas/__init__.py
ucloud/services/iam/schemas/apis.py
ucloud/services/iam/schemas/models.py
ucloud/services/ipsecvpn/__init__.py
ucloud/services/ipsecvpn/client.py
ucloud/services/ipsecvpn/schemas/__init__.py
ucloud/services/ipsecvpn/schemas/apis.py
ucloud/services/ipsecvpn/schemas/models.py
ucloud/services/ipv6gw/__init__.py
ucloud/services/ipv6gw/client.py
ucloud/services/ipv6gw/schemas/__init__.py
ucloud/services/ipv6gw/schemas/apis.py
ucloud/services/ipv6gw/schemas/models.py
ucloud/services/isms/__init__.py
ucloud/services/isms/client.py
ucloud/services/isms/schemas/__init__.py
ucloud/services/isms/schemas/apis.py
ucloud/services/isms/schemas/models.py
ucloud/services/pathx/__init__.py
ucloud/services/pathx/client.py
ucloud/services/pathx/schemas/__init__.py
ucloud/services/pathx/schemas/apis.py
ucloud/services/pathx/schemas/models.py
ucloud/services/stepflow/__init__.py
ucloud_sdk_python3-0.11.83.dist-info/LICENSE
ucloud_sdk_python3-0.11.83.dist-info/METADATA
ucloud_sdk_python3-0.11.83.dist-info/WHEEL
ucloud_sdk_python3-0.11.83.dist-info/top_level.txt
ucloud_sdk_python3-0.11.83.dist-info/RECORD
