Metadata-Version: 2.1
Name: ucloud-sdk-python3
Version: 0.11.83
Summary: UCloud Service Development Kit - Python
Home-page: https://github.com/ucloud/ucloud-sdk-python3
Author: ucloud
Author-email: esl_ipdd@ucloud.cn
License: Apache License 2.0
Platform: UNKNOWN
Classifier: Development Status :: 3 - Alpha
Classifier: Environment :: Console
Classifier: Environment :: Web Environment
Classifier: Intended Audience :: Developers
Classifier: Intended Audience :: System Administrators
Classifier: License :: OSI Approved :: Apache Software License
Classifier: Programming Language :: Python :: 3 :: Only
Classifier: Programming Language :: Python :: 3.5
Classifier: Programming Language :: Python :: 3.6
Classifier: Programming Language :: Python :: 3.7
Classifier: Topic :: Software Development
Requires-Python: >=3.5
License-File: LICENSE
Requires-Dist: requests
Provides-Extra: ci
Requires-Dist: flake8 (>=3.6.0) ; extra == 'ci'
Requires-Dist: pytest (>=4.6) ; extra == 'ci'
Requires-Dist: requests ; extra == 'ci'
Requires-Dist: pytest-cov ; extra == 'ci'
Requires-Dist: sphinx ; extra == 'ci'
Requires-Dist: requests-mock ; extra == 'ci'
Provides-Extra: dev
Requires-Dist: flake8 (>=3.6.0) ; extra == 'dev'
Requires-Dist: black ; extra == 'dev'
Requires-Dist: requests ; extra == 'dev'
Requires-Dist: pytest (>=4.6) ; extra == 'dev'
Requires-Dist: pytest-cov ; extra == 'dev'
Requires-Dist: sphinx ; extra == 'dev'
Requires-Dist: requests-mock ; extra == 'dev'
Provides-Extra: doc
Requires-Dist: requests ; extra == 'doc'
Requires-Dist: sphinx ; extra == 'doc'
Provides-Extra: test
Requires-Dist: requests ; extra == 'test'
Requires-Dist: flake8 (>=3.6.0) ; extra == 'test'
Requires-Dist: pytest (>=4.6) ; extra == 'test'
Requires-Dist: pytest-cov ; extra == 'test'
Requires-Dist: requests-mock ; extra == 'test'
